Metadata-Version: 2.4
Name: qqqwww123_x
Version: 0.1
Summary: geoestadistica
Home-page: https://github.com/fededimant/qqqwww123_x
Author: fede
Author-email: fededimant@hotmail.com
Dynamic: author
Dynamic: author-email
Dynamic: home-page
Dynamic: summary
